PyOpenMagnetics.cpython-310-x86_64-linux-gnu.so
include/pybind11_json/pybind11_json.hpp
share/cmake/pybind11_json/pybind11_jsonConfigVersion.cmake
share/cmake/pybind11_json/pybind11_jsonConfig.cmake
share/cmake/pybind11_json/pybind11_jsonTargets.cmake
share/pkgconfig/pybind11_json.pc
pyopenmagnetics-1.1.2.dist-info/METADATA
pyopenmagnetics-1.1.2.dist-info/WHEEL
pyopenmagnetics-1.1.2.dist-info/RECORD
pyopenmagnetics-1.1.2.dist-info/licenses/LICENSE
