Metadata-Version: 2.2
Name: PyOpenMagnetics
Version: 1.1.2
Summary: Python wrapper for OpenMagnetics
Author-Email: Alfonso Martinez <Alfonso_VII@hotmail.com>
Classifier: Development Status :: 4 - Beta
Classifier: Programming Language :: Python :: 3
Classifier: Operating System :: Microsoft :: Windows :: Windows 11
Classifier: Operating System :: POSIX :: Linux
Classifier: Programming Language :: C++
Classifier: License :: OSI Approved :: MIT License
Project-URL: Homepage, https://openmagnetics.com
Project-URL: Repository, https://github.com/OpenMagnetics/PyOpenMagnetics
Project-URL: Contact, https://www.linkedin.com/in/alfonso-martinez-de-la-torre/
Requires-Python: >=3.8
